can_cvector/__init__.py
can_cvector/_abstraction.cp313-win32.pyd
can_cvector/_abstraction.pyi
can_cvector/_version.py
can_cvector/cvector.py
can_cvector/py.typed
can_cvector/vxlapi/__init__.py
python_can_cvector-1.6.0.dist-info/METADATA
python_can_cvector-1.6.0.dist-info/WHEEL
python_can_cvector-1.6.0.dist-info/entry_points.txt
python_can_cvector-1.6.0.dist-info/licenses/LICENSE
python_can_cvector-1.6.0.dist-info/RECORD
