Metadata-Version: 2.2
Name: python-can-cvector
Version: 1.6.0
Summary: A partly cythonized version of the python-can VectorBus
Keywords: python-can,CAN,vector,cython
Author-Email: Artur Drogunow <artur.drogunow@zf.com>
License: LGPL v3
Classifier: Programming Language :: Cython
Classifier: Programming Language :: Python
Classifier: Programming Language :: Python :: 3.8
Classifier: Programming Language :: Python :: 3.9
Classifier: Programming Language :: Python :: 3.10
Classifier: Programming Language :: Python :: 3.11
Classifier: Programming Language :: Python :: 3.12
Classifier: Programming Language :: Python :: 3.13
Classifier: Programming Language :: Python :: 3.14
Classifier: Programming Language :: Python :: Implementation :: CPython
Classifier: Programming Language :: Python :: Implementation :: PyPy
Classifier: Programming Language :: Python :: Free Threading :: 1 - Unstable
Classifier: Operating System :: Microsoft :: Windows
Classifier: Intended Audience :: Developers
Project-URL: Documentation, https://github.com/zariiii9003/python-can-cvector#readme
Project-URL: Issues, https://github.com/zariiii9003/python-can-cvector/issues
Project-URL: Source, https://github.com/zariiii9003/python-can-cvector
Project-URL: Homepage, https://github.com/zariiii9003/python-can-cvector
Requires-Python: >=3.8
Requires-Dist: python-can==4.*
Provides-Extra: dev
Requires-Dist: black==24.4.*; extra == "dev"
Requires-Dist: cibuildwheel; extra == "dev"
Requires-Dist: mypy==1.10.*; extra == "dev"
